cpg2py/__init__.py
cpg2py/_exceptions.py
cpg2py/_logger.py
cpg2py/_abc/__init__.py
cpg2py/_abc/edge.py
cpg2py/_abc/graph.py
cpg2py/_abc/node.py
cpg2py/_abc/storage.py
cpg2py/_cpg/__init__.py
cpg2py/_cpg/edge.py
cpg2py/_cpg/graph.py
cpg2py/_cpg/node.py
cpg2py-1.1.0.dist-info/LICENSE
cpg2py-1.1.0.dist-info/METADATA
cpg2py-1.1.0.dist-info/WHEEL
cpg2py-1.1.0.dist-info/top_level.txt
cpg2py-1.1.0.dist-info/RECORD
