Metadata-Version: 2.1
Name: cpg2py
Version: 1.1.0
Summary: A graph-based data structure designed for querying CSV files in Joern format in Python
Author-email: samhsu-dev <yxu166@jhu.edu>
License: MIT License
Project-URL: Homepage, https://github.com/YichaoXu/cpg2py
Project-URL: Repository, https://github.com/YichaoXu/cpg2py
Project-URL: Documentation, https://github.com/YichaoXu/cpg2py
Keywords: Joern,CPG,Graph,CSV
Classifier: Development Status :: 4 - Beta
Classifier: Intended Audience :: Developers
Classifier: License :: OSI Approved :: MIT License
Classifier: Programming Language :: Python :: 3
Classifier: Programming Language :: Python :: 3.8
Classifier: Programming Language :: Python :: 3.9
Classifier: Programming Language :: Python :: 3.10
Classifier: Programming Language :: Python :: 3.11
Classifier: Programming Language :: Python :: 3.12
Classifier: Topic :: Software Development :: Libraries :: Python Modules
Requires-Python: >=3.8
License-File: LICENSE
Provides-Extra: dev
Requires-Dist: pytest>=7.0.0; extra == "dev"
Requires-Dist: pytest-cov>=4.0.0; extra == "dev"
Provides-Extra: test
